cmsplugin_google_maps_ai/__init__.py
cmsplugin_google_maps_ai/apps.py
cmsplugin_google_maps_ai/cms_plugins.py
cmsplugin_google_maps_ai/models.py
cmsplugin_google_maps_ai/migrations/0001_initial.py
cmsplugin_google_maps_ai/migrations/__init__.py
cmsplugin_google_maps_ai-0.0.1.dist-info/DESCRIPTION.rst
cmsplugin_google_maps_ai-0.0.1.dist-info/METADATA
cmsplugin_google_maps_ai-0.0.1.dist-info/RECORD
cmsplugin_google_maps_ai-0.0.1.dist-info/WHEEL
cmsplugin_google_maps_ai-0.0.1.dist-info/metadata.json
cmsplugin_google_maps_ai-0.0.1.dist-info/top_level.txt
