Metadata-Version: 2.0
Name: cmsplugin-google-maps-ai
Version: 0.0.1
Summary: Google Maps embed plugin for Django CMS
Home-page: https://github.com/andersinno/cmsplugin-google-maps-ai
Author: Anders Innovations
Author-email: info@anders.fi
License: MIT
Platform: UNKNOWN
Requires-Dist: django-cms (>=3.2,<3.5)
